{
  "updatedAt": "2026-05-22T20:32:14.804Z",
  "source": "AV:11+CoinGecko:3",
  "assets": [
    {
      "symbol": "BTC",
      "name": "Bitcoin",
      "price": 75818,
      "change1d": -2.38,
      "change7d": -4.18
    },
    {
      "symbol": "GOLD",
      "name": "Gold (GLD)",
      "price": 413.87,
      "change1d": -0.75,
      "change7d": -0.82
    },
    {
      "symbol": "NVDA",
      "name": "NVIDIA",
      "price": 215.33,
      "change1d": -1.9,
      "change7d": -4.43
    },
    {
      "symbol": "TSLA",
      "name": "Tesla",
      "price": 426.01,
      "change1d": 1.95,
      "change7d": 0.89
    },
    {
      "symbol": "META",
      "name": "Meta",
      "price": 610.26,
      "change1d": 0.47,
      "change7d": -0.65
    },
    {
      "symbol": "GOOGL",
      "name": "Alphabet",
      "price": 382.97,
      "change1d": -1.21,
      "change7d": -3.48
    },
    {
      "symbol": "AMD",
      "name": "AMD",
      "price": 467.51,
      "change1d": 3.99,
      "change7d": 10.24
    },
    {
      "symbol": "AAOI",
      "name": "Applied Optoelectronics",
      "price": 181.49,
      "change1d": 2.65,
      "change7d": -4.66
    },
    {
      "symbol": "AXTI",
      "name": "AXT Inc",
      "price": 140.83,
      "change1d": 16.37,
      "change7d": 13.77
    },
    {
      "symbol": "AAPL",
      "name": "Apple",
      "price": 308.82,
      "change1d": 1.26,
      "change7d": 2.86
    },
    {
      "symbol": "MSFT",
      "name": "Microsoft",
      "price": 418.57,
      "change1d": -0.12,
      "change7d": -0.79
    },
    {
      "symbol": "AMZN",
      "name": "Amazon",
      "price": 266.32,
      "change1d": -0.8,
      "change7d": 0.83
    },
    {
      "symbol": "ETH",
      "name": "Ethereum",
      "price": 2067.9,
      "change1d": -3.28,
      "change7d": -6.96
    },
    {
      "symbol": "SOL",
      "name": "Solana",
      "price": 84.65,
      "change1d": -3.45,
      "change7d": -5.31
    }
  ]
}
