{
  "updatedAt": "2026-05-06T15:45:13.790Z",
  "source": "AV:11+CoinGecko:3",
  "assets": [
    {
      "symbol": "BTC",
      "name": "Bitcoin",
      "price": 81523,
      "change1d": -0.15,
      "change7d": 6.18
    },
    {
      "symbol": "GOLD",
      "name": "Gold (GLD)",
      "price": 418.27,
      "change1d": 0.86,
      "change7d": -0.86
    },
    {
      "symbol": "NVDA",
      "name": "NVIDIA",
      "price": 196.5,
      "change1d": -1,
      "change7d": -7.82
    },
    {
      "symbol": "TSLA",
      "name": "Tesla",
      "price": 389.37,
      "change1d": -0.8,
      "change7d": 3.55
    },
    {
      "symbol": "META",
      "name": "Meta",
      "price": 604.96,
      "change1d": -0.89,
      "change7d": -9.89
    },
    {
      "symbol": "GOOGL",
      "name": "Alphabet",
      "price": 388.43,
      "change1d": 1.35,
      "change7d": 11.05
    },
    {
      "symbol": "AMD",
      "name": "AMD",
      "price": 355.26,
      "change1d": 4.02,
      "change7d": 9.92
    },
    {
      "symbol": "AAOI",
      "name": "Applied Optoelectronics",
      "price": 180.57,
      "change1d": 4.39,
      "change7d": 31.55
    },
    {
      "symbol": "AXTI",
      "name": "AXT Inc",
      "price": 107.55,
      "change1d": 1.46,
      "change7d": 56.53
    },
    {
      "symbol": "AAPL",
      "name": "Apple",
      "price": 284.18,
      "change1d": 2.66,
      "change7d": 4.98
    },
    {
      "symbol": "MSFT",
      "name": "Microsoft",
      "price": 411.38,
      "change1d": -0.54,
      "change7d": -4.16
    },
    {
      "symbol": "AMZN",
      "name": "Amazon",
      "price": 273.55,
      "change1d": 0.55,
      "change7d": 5.33
    },
    {
      "symbol": "ETH",
      "name": "Ethereum",
      "price": 2356.78,
      "change1d": -1.21,
      "change7d": 2.36
    },
    {
      "symbol": "SOL",
      "name": "Solana",
      "price": 88.57,
      "change1d": 3.49,
      "change7d": 5.48
    }
  ]
}
